{
    "title": "Mad Truck Challenge Special",
    "title_blog": "Mastering Mad Truck Challenge Special: Top Tips and Tricks to Beat the Game",
    "meta_description": "Play Mad Truck Challenge Special unblock game directly in your browser without download, featuring intense truck racing and addictive gameplay.",
    "meta_description_blog": "\"Master the Mad Truck Challenge Special with expert tips and strategies to unlock levels and dominate the unblocked game.\"",
    "description": "<strong>Get ready for the ultimate driving experience with the <strong>Mad Truck Challenge Special Unblock Game<\/strong>!<\/strong> This adrenaline-fueled browser game is all about crushing obstacles, collecting coins, and upgrading your rig to become the ultimate trucking champion. With its simple yet addictive gameplay, <strong>Mad Truck Challenge Special<\/strong> is a must-play for fans of racing and driving games.\n\n<h2>Core Gameplay Loop and Win Condition<\/h2>\n\n<p>The game starts with a simple goal: drive your truck through a challenging obstacle course without crashing. As you progress, the levels become increasingly difficult, with new obstacles, twists, and turns to navigate. Your ultimate goal is to reach the end of each level without losing a life.<\/p>\n\n<p>The core gameplay loop involves driving through the course, collecting coins, and upgrading your truck's performance. You can upgrade your truck's speed, durability, and handling to make it more agile and responsive. The game also features a variety of power-ups and bonuses to help you overcome obstacles and stay ahead of the competition.<\/p>\n\n<p>As you progress through the levels, the game becomes increasingly challenging, with new obstacles and challenges to overcome. You'll need to use your skills and reflexes to navigate the course and reach the end of each level.<\/p>\n\n<h2>Controls and Gameplay Mechanics<\/h2>\n\n<p>The controls in <strong>Mad Truck Challenge Special<\/strong> are simple yet intuitive. On desktop, you can use the arrow keys or WASD keys to control your truck's movement. On mobile, you can use touch controls to steer your truck left and right. The game also features a variety of buttons and controls to help you navigate the course and execute jumps and other maneuvers.<\/p>\n\n<p>The game also features a variety of gameplay mechanics, including jumps, flips, and power-ups. You can use these mechanics to overcome obstacles and stay ahead of the competition. The game also features a variety of environments and levels, including deserts, forests, and cities.<\/p>\n\n<p>One of the unique features of <strong>Mad Truck Challenge Special<\/strong> is its adaptive controls. The game adjusts its controls to suit your playing style, making it easier to play on mobile devices or desktop computers.<\/p>\n\n<h2>Performance and Browser Compatibility<\/h2>\n\n<p><strong>Mad Truck Challenge Special<\/strong> is a browser-based game that runs smoothly on most modern browsers, including Google Chrome, Mozilla Firefox, and Safari. The game is also optimized for mobile devices, making it easy to play on-the-go.<\/p>\n\n<p>One of the benefits of playing <strong>Mad Truck Challenge Special<\/strong> online is that you don't need to download any software or plugins. The game runs directly in your browser, making it easy to access and play.<\/p>\n\n<p>The game also features a variety of performance-enhancing features, including graphics optimization and sound effects. These features help to create a smooth and immersive gaming experience, even on lower-end devices.<\/p>\n\n<h2>Tips and Strategies for Beginners and Intermediate Players<\/h2>\n\n<ul>\n\t<li>Start with the easier levels and gradually move on to more challenging ones.<\/li>\n\t<li>Practice your skills and reflexes to improve your driving and maneuvering abilities.<\/li>\n\t<li>Use your power-ups and bonuses strategically to overcome obstacles and stay ahead of the competition.<\/li>\n\t<li>Upgrade your truck's performance regularly to stay competitive.<\/li>\n<\/ul>\n\n<p>As a beginner, focus on mastering the basic controls and gameplay mechanics. Practice your skills and reflexes to improve your driving and maneuvering abilities. As you progress, you can use your power-ups and bonuses strategically to overcome obstacles and stay ahead of the competition.<\/p>\n\n<h2>Why Play <strong>Mad Truck Challenge Special<\/strong>?<\/h3>\n\n<p><strong>Mad Truck Challenge Special<\/strong> is the perfect game for fans of racing and driving games. The game's simple yet addictive gameplay, combined with its high replay value and variety of levels and challenges, make it a must-play for anyone looking for a fun and exciting gaming experience.<\/p>\n\n<p>The game is also great for players of all ages and skill levels. Whether you're a beginner or an experienced gamer, you'll find something to enjoy in <strong>Mad Truck Challenge Special<\/strong>. The game's easy-to-use controls and adaptive gameplay make it accessible to players of all ages and skill levels.<\/p>\n\n<h2>Comparison of Modes and Difficulty Levels<\/h2>\n\n<table>\n\t<thead>\n\t\t<tr>\n\t\t\t<th>Mode<\/th>\n\t\t\t<th>Difficulty Level<\/th>\n\t\t\t<th>Recommended Strategy<\/th>\n\t\t\t<th>Common Mistakes<\/th>\n\t\t<\/tr>\n\t<\/thead>\n\t<tbody>\n\t\t<tr>\n\t\t\t<td>Time Attack<\/td>\n\t\t\t<td>Easy<\/td>\n\t\t\t<td>Focus on speed and accuracy.<\/td>\n\t\t\t<td>Don't get too attached to a particular route or strategy.<\/td>\n\t\t<\/tr>\n\t\t<tr>\n\t\t\t<td>Survival Mode<\/td>\n\t\t\t<td>Medium<\/td>\n\t\t\t<td>Use your power-ups and bonuses strategically to overcome obstacles.<\/td>\n\t\t\t<td>Don't underestimate the difficulty of the levels.<\/td>\n\t\t<\/tr>\n\t\t<tr>\n\t\t\t<td>Championship Mode<\/td>\n\t\t\t<td>Hard<\/td>\n\t\t\t<td>Practice your skills and reflexes to improve your driving and maneuvering abilities.<\/td>\n\t\t\t<td>Don't get discouraged by setbacks and losses.<\/td>\n\t\t<\/tr>\n\t<\/tbody>\n<\/table>\n\n<h2>Who is <strong>Mad Truck Challenge Special<\/strong> Best For?<\/h2>\n\n<p><strong>Mad Truck Challenge Special<\/strong> is best for fans of racing and driving games. The game's simple yet addictive gameplay, combined with its high replay value and variety of levels and challenges, make it a must-play for anyone looking for a fun and exciting gaming experience.<\/p>\n\n<p>The game is also great for players of all ages and skill levels. Whether you're a beginner or an experienced gamer, you'll find something to enjoy in <strong>Mad Truck Challenge Special<\/strong>. The game's easy-to-use controls and adaptive gameplay make it accessible to players of all ages and skill levels.<\/p>",
    "description_alt": "<h2><strong>Mad Truck Challenge Special Unblock Game: Tips and Tricks<\/strong><\/h2>\n<p>Are you ready for an adrenaline-fueled experience that will put your driving skills to the test? Look no further than the <strong>Mad Truck Challenge Special Unblock Game<\/strong>, a thrilling browser-based game that's perfect for a quick break at school or work.<\/p>\n<p>With its addictive gameplay and simple controls, this game is easy to pick up but difficult to master. In this article, we'll show you how to play Mad Truck Challenge Special like a pro, covering common mistakes, strategy progression, and more.<\/p>\n<p>Whether you're a seasoned gamer or just looking for a fun way to pass the time, this game has something for everyone. So, let's dive in and explore the world of Mad Truck Challenge Special!<\/p>\n\n<h2>Replayability and Difficulty Spikes<\/h2>\n<p>One of the key factors that makes Mad Truck Challenge Special so engaging is its replayability. The game features procedurally generated levels, ensuring that no two playthroughs are alike. As you progress through the levels, the difficulty gradually increases, but it's not just a straightforward progression.<\/p>\n<p>Difficulty spikes occur when you encounter new obstacles or challenges that require you to adapt your driving style. For example, you might encounter a level with a steep incline or a narrow bridge that requires precise timing and control.<\/p>\n<p>Don't worry, though - with practice and patience, you'll be able to overcome these challenges and continue your upward trajectory.<\/p>\n\n<h2>Common Player Mistakes and How to Fix Them<\/h2>\n<p>As with any game, there are common mistakes that players make when starting out. Here are a few examples:<\/p>\n<ul>\n\t<li>Not checking the map before starting a level: Make sure to take a glance at the map before embarking on a new level to get an idea of the layout and potential hazards.<\/li>\n\t<li>Not using the right gear: Failing to use the correct gear can lead to slow acceleration and poor control. Pay attention to the gear indicator and shift gears accordingly.<\/li>\n\t<li>Not braking in time: Not braking in time can cause your truck to skid or even crash. Make sure to use your brakes smoothly and in advance.<\/li>\n<\/ul>\n\n<h2>Strategy Progression: From Beginner to Master<\/h2>\n<p>As you progress through the game, your strategy will evolve. Here's a rough outline of what you can expect:<\/p>\n<p>**First 10 minutes:** At this stage, you're still getting used to the controls and learning the basics. Focus on getting familiar with the game's mechanics and developing a feel for the truck's handling.<\/p>\n<p>**After basics:** Once you've got the hang of the controls, focus on improving your driving skills. Practice drifting, jumping, and using your brakes smoothly.<\/p>\n<p>**Mastery phase:** At this stage, you're a seasoned pro, and it's time to take your gameplay to the next level. Focus on optimizing your route, using your speed boosts wisely, and perfecting your driving techniques.<\/p>\n\n<h2>Mobile Friendliness and School\/Work Break Suitability<\/h2>\n<p>One of the best things about Mad Truck Challenge Special is its mobile-friendly design. You can play the game on your phone or tablet, making it the perfect way to spend a quick break at school or work.<\/p>\n<p>Whether you're on a short break or have a few minutes to spare, this game is the perfect way to unwind and have some fun. Plus, with no installation required, you can start playing right away.<\/p>\n\n<h2>Comparison Table: Mad Truck Challenge Special vs. Similar Browser Games<\/h2>\n<table>\n\t<thead>\n\t\t<tr>\n\t\t\t<th>Game<\/th>\n\t\t\t<th>Pace<\/th>\n\t\t\t<th>Skill Ceiling<\/th>\n\t\t\t<th>Session Length<\/th>\n\t\t\t<th>Accessibility<\/th>\n\t\t<\/tr>\n\t<\/thead>\n\t<tbody>\n\t\t<tr>\n\t\t\t<td>Mad Truck Challenge Special<\/td>\n\t\t\t<td>Fast-paced<\/td>\n\t\t\t<td>High<\/td>\n\t\t\t<td>5-10 minutes<\/td>\n\t\t\t<td>High<\/td>\n\t\t<\/tr>\n\t\t<tr>\n\t\t\t<td>Truck Driver<\/td>\n\t\t\t<td>Medium-paced<\/td>\n\t\t\t<td>Medium<\/td>\n\t\t\t<td>10-20 minutes<\/td>\n\t\t\t<td>Medium<\/td>\n\t\t<\/tr>\n\t\t<tr>\n\t\t\t<td>Offroad Racing<\/td>\n\t\t\t<td>Fast-paced<\/td>\n\t\t\t<td>High<\/td>\n\t\t\t<td>5-10 minutes<\/td>\n\t\t\t<td>Low<\/td>\n\t\t<\/tr>\n\t\t<tr>\n\t\t\t<td>Truck Simulator<\/td>\n\t\t\t<td>Medium-paced<\/td>\n\t\t\t<td>Low<\/td>\n\t\t\t<td>20-30 minutes<\/td>\n\t\t\t<td>High<\/td>\n\t\t<\/tr>\n\t<\/tbody>\n<\/table>\n\n<h2>Pros and Cons of Playing Mad Truck Challenge Special<\/h2>\n<ul>\n\t<li>Pros:\n\t\t<ul>\n\t\t\t<li>Fast-paced and addictive gameplay<\/li>\n\t\t\t<li>Simple controls and intuitive gameplay<\/li>\n\t\t\t<li>Procedurally generated levels for high replayability<\/li>\n\t\t\t<li>Mobile-friendly design for on-the-go play<\/li>\n\t\t<\/ul>\n\t<\/li>\n\t<li>Cons:\n\t\t<ul>\n\t\t\t<li>Difficulty spikes can be frustrating<\/li>\n\t\t\t<li>Limited game modes and features<\/li>\n\t\t\t<li>No multiplayer or online features<\/li>\n\t\t<\/ul>\n\t<\/li>\n<\/ul>",
    "questions": [
        {
            "question": "What is Mad Truck Challenge Special all about?",
            "answer": "Mad Truck Challenge Special is an action-packed driving game where you control a rugged truck, navigating through challenging terrain and obstacles to reach the finish line. The game offers a variety of trucks to choose from, each with its unique abilities and strengths. Get ready to experience the thrill of off-road racing!"
        },
        {
            "question": "How do I control the truck in Mad Truck Challenge Special?",
            "answer": "In Mad Truck Challenge Special, you can control the truck using the arrow keys or WASD keys on your keyboard. You can also use your mouse to steer the truck, but be cautious not to get stuck in tight spaces. Experiment with different control settings to find what works best for you!"
        },
        {
            "question": "Is Mad Truck Challenge Special difficult to play?",
            "answer": "Mad Truck Challenge Special offers varying levels of difficulty to suit different players. As you progress through the game, the challenges become increasingly tougher, requiring precise timing, quick reflexes, and strategic thinking. Don't worry, you can adjust the difficulty level to suit your skills!"
        },
        {
            "question": "Can I play Mad Truck Challenge Special on my mobile device?",
            "answer": "Yes, Mad Truck Challenge Special is optimized for mobile play, and you can enjoy it on your smartphone or tablet. However, be aware that some features and controls might be slightly different than on PC or laptop. Make sure to check the system requirements for your device before playing!"
        },
        {
            "question": "Why can't I access Mad Truck Challenge Special on some websites?",
            "answer": "Mad Truck Challenge Special is often available as a unblocked game on many websites, but some sites might restrict access due to copyright or licensing issues. Don't worry, you can still play the game on other websites or download it from the official website to access it freely!"
        },
        {
            "question": "Do I need to download anything to play Mad Truck Challenge Special?",
            "answer": "No, you can play Mad Truck Challenge Special directly in your web browser without any downloads or installations required. Just visit the game's website, and you're ready to roll!"
        },
        {
            "question": "Is Mad Truck Challenge Special safe to play?",
            "answer": "Mad Truck Challenge Special is a safe and virus-free game, and you can play it without worrying about malware or adware. However, always be cautious when downloading games from unknown sources, and stick to reputable websites for the best gaming experience!"
        },
        {
            "question": "How do I troubleshoot issues with Mad Truck Challenge Special?",
            "answer": "If you encounter any issues with Mad Truck Challenge Special, try refreshing the page, clearing your cache, or checking your internet connection. If the problem persists, try visiting the game's official website or contacting the developer for technical support!"
        },
        {
            "question": "Can I play Mad Truck Challenge Special with friends?",
            "answer": "While Mad Truck Challenge Special is primarily designed for solo play, you can still challenge yourself to beat your own records or compete with friends in local multiplayer mode. Just be aware that some features and modes might be limited to single-player or online play."
        },
        {
            "question": "How do I get help or support for Mad Truck Challenge Special?",
            "answer": "For any questions, feedback, or technical issues with Mad Truck Challenge Special, you can visit the game's official website, check out the FAQs, or contact the developer directly. They'll be happy to assist you and provide you with the best gaming experience!"
        }
    ],
    "related_keywords": [
        "mad truck challenge special unblocked game",
        "mad truck challenge special online game",
        "mad truck challenge special browser game",
        "mad truck challenge special no download game",
        "mad truck challenge special gameplay tips",
        "mad truck challenge special controls guide",
        "how to play mad truck challenge special",
        "mad truck challenge special mobile game",
        "mad truck challenge special strategy guide",
        "similar games to mad truck challenge special",
        "mad truck challenge special walkthrough",
        "mad truck challenge special cheats",
        "mad truck challenge special no flash game",
        "mad truck challenge special html5 game",
        "mad truck challenge special game online free",
        "mad truck challenge special play now",
        "mad truck challenge special unblocker",
        "mad truck challenge special free to play",
        "mad truck challenge special game review",
        "mad truck challenge special game download alternatives"
    ]
}