{
    "title": "Bouncy Basketball",
    "title_blog": "Mastering Bouncy Basketball Unblock Game Ultimate Tips",
    "meta_description": "\"Get ready to bounce your way to fun! Play Bouncy Basketball, a free unblock game, directly in your browser without download, and test your skills with each challenging level.\"",
    "meta_description_blog": "\"Master the art of bouncy basketball unblock game with expert tips on strategy and gameplay to take your skills to the next level!\"",
    "description": "<strong>Bouncy Basketball Unblock Game</strong> has taken the online gaming community by storm with its simple yet addictive gameplay. This browser-based game is perfect for players looking for a quick, fun experience that can be played on any device with a web browser.\n\n<h2>Core Gameplay Loop and Win Condition</h2>\n\nIn Bouncy Basketball, the goal is to navigate a ball through a maze-like court using a combination of mouse clicks or touch inputs to control the ball's trajectory. The game features multiple levels, each with its unique layout and obstacles. Players must use their timing and spatial reasoning skills to guide the ball through the court, collecting power-ups and avoiding enemies along the way. The ultimate goal is to clear each level by getting the ball into the hoop.\n\nPlayers can expect a relaxing yet challenging experience as they progress through the levels. The game's win condition is to complete each level within the given time limit or score as many points as possible. The game's simplicity makes it accessible to players of all ages and skill levels, but the increasing difficulty and complexity of the levels add a layer of challenge that keeps players engaged.\n\n<h2>Controls and Desktop/Mobile Adaptation</h2>\n\nThe controls for Bouncy Basketball are straightforward and easy to use. Players can control the ball's movement using the mouse on desktop devices or by swiping their finger on mobile devices. The game's intuitive controls make it easy to pick up and play, even for players who are new to browser games. The game's developers have also optimized the controls to work seamlessly on both desktop and mobile devices, ensuring a smooth gaming experience across different platforms.\n\nPlayers can use the mouse to click and drag the ball to control its movement or use the touchpad to swipe their finger across the screen. The game's mobile adaptation is particularly impressive, with the controls adapting to the touch-based input method. This ensures that players can enjoy the game on-the-go, anytime and anywhere.\n\n<h2>Beginner and Intermediate Tips</h2>\n\nFor players who are new to Bouncy Basketball, here are some beginner tips to get you started:\n\n\n\n* Start by getting familiar with the controls and the game's mechanics. Practice moving the ball around the court to get a feel for the game.\n\n\n* Focus on collecting power-ups and using them strategically to clear the level.\n\n\n* Use the ball's bounce to your advantage by timing your clicks or swipes to maximize the ball's movement.\n\n\n* As you progress through the levels, pay attention to the obstacles and enemies on the court and plan your movement accordingly.\n\nFor intermediate players, here are some advanced tips to help you improve your gameplay:\n\n\n\n* Use the ball's speed and momentum to your advantage by timing your clicks or swipes to maximize the ball's movement.\n\n\n* Learn to control the ball's movement by adjusting the angle and speed of your inputs.\n\n\n* Experiment with different power-ups and strategies to clear the level.\n\n\n* Pay attention to the level's layout and use your spatial reasoning skills to navigate the ball through the court.\n\n<h2>Performance, Browser Compatibility, and Quick-Load/No-Download Value</h2>\n\nBouncy Basketball is a well-optimized game that runs smoothly on most devices with a modern web browser. Players can expect a fast and responsive gaming experience, with the game loading quickly and running without any noticeable lag. The game's browser-based design also means that players can access it from anywhere, without the need to download or install any software.\n\nThe game's performance is also impressive, with the game's developers using advanced technologies to optimize the game for different devices and browsers. Players can expect a consistent and high-quality gaming experience, regardless of their device or browser.\n\n<h2>Who is Bouncy Basketball Best For?</h2>\n\nBouncy Basketball is best suited for players who are looking for a fun and relaxing gaming experience that can be played on-the-go. The game's simplicity and accessibility make it perfect for players of all ages and skill levels, while its increasing difficulty and complexity add a layer of challenge that keeps players engaged.\n\nThe game is also ideal for players who are looking for a quick pick-me-up or a way to pass the time. The game's short levels and easy-to-use controls make it easy to play in short sessions, and the game's browser-based design means that players can access it from anywhere.\n\n<h2>Common Mistakes and Strategies</h2>\n\nHere is a comparison of different level modes, difficulties, recommended strategies, and common mistakes:\n\n<table>\n  <thead>\n    <tr>\n      <th>Level Mode</th>\n      <th>Difficulty</th>\n      <th>Recommended Strategy</th>\n      <th>Common Mistakes</th>\n    </tr>\n  </thead>\n  <tbody>\n    <tr>\n      <td>Easy</td>\n      <td>Beginner-friendly</td>\n      <td>Focus on collecting power-ups and using them strategically</td>\n      <td>Not paying attention to obstacles and enemies</td>\n    </tr>\n    <tr>\n      <td>Medium</td>\n      <td>Challenging</td>\n      <td>Use the ball's speed and momentum to your advantage</td>\n      <td>Not adjusting the angle and speed of your inputs</td>\n    </tr>\n    <tr>\n      <td>Hard</td>\n      <td>Expert-level</td>\n      <td>Experiment with different power-ups and strategies</td>\n      <td>Not paying attention to the level's layout</td>\n    </tr>\n  </tbody>\n</table>\n\nFor players who are new to Bouncy Basketball, here are some additional tips to help you avoid common mistakes:\n\n\n\n* Pay attention to the obstacles and enemies on the court and plan your movement accordingly.\n\n\n* Use the ball's bounce to your advantage by timing your clicks or swipes to maximize the ball's movement.\n\n\n* Experiment with different power-ups and strategies to clear the level.\n\nBy following these tips and strategies, players can improve their gameplay and enjoy a more challenging and rewarding experience in Bouncy Basketball.",
    "description_alt": "<h2><strong>Bouncy Basketball Unblock Game: A Thrilling Experience for Basketball Fans</strong></h2>\n\n<p>Get ready to experience the ultimate basketball thrill in the <strong>bouncy basketball unblock game</strong>, a browser-based game that combines addictive gameplay with realistic basketball action. With its intuitive controls and smooth animations, this game is perfect for both casual and hardcore basketball fans. In this article, we'll delve into the world of <strong>bouncy basketball</strong>, exploring its replayability, difficulty spikes, common player mistakes, and strategies for progression.</p>\n\n<h2>Replayability and Difficulty Spikes</h2>\n\n<p>The <strong>bouncy basketball unblock game</strong> offers a high replay value due to its procedurally generated levels, ensuring that each game session is unique. As players progress through the game, the difficulty spikes become more frequent and intense, challenging even the most skilled players. The game's AI adapts to the player's performance, making it essential to stay focused and improve your skills to overcome the increasing difficulty.</p>\n\n<p>The difficulty spikes occur at specific milestones, such as reaching a certain level, achieving a specific score, or completing a challenging level. At these points, the game's pace accelerates, and the obstacles become more complex, requiring players to adapt their strategy and improve their reflexes.</p>\n\n<h2>Common Player Mistakes and How to Fix Them</h2>\n\n<p>Many players make common mistakes that hinder their progress in the <strong>bouncy basketball unblock game</strong>. One of the most significant mistakes is failing to anticipate the ball's trajectory, leading to missed shots or collisions with obstacles. To avoid this, players should focus on developing their spatial awareness and timing.</p>\n\n<p>Another common mistake is not adjusting to the game's increasing difficulty. As players progress, the game's AI becomes more aggressive, and the obstacles become more complex. To overcome this, players should regularly review their gameplay, identify areas for improvement, and adjust their strategy accordingly.</p>\n\n<h2>Strategy Progression: From Basics to Mastery</h3>\n\n<p>The <strong>bouncy basketball unblock game</strong> offers a clear progression path, allowing players to improve their skills and unlock new levels. In the first 10 minutes, players should focus on mastering the basic controls and understanding the game's mechanics. As they progress, they should focus on developing their timing and spatial awareness, and learning to anticipate the ball's trajectory.</p>\n\n<p>After mastering the basics, players can focus on developing more advanced strategies, such as using the obstacles to their advantage, and learning to control the ball's speed and direction. In the mastery phase, players should aim to achieve a high level of consistency, accuracy, and speed, and experiment with different techniques to stay ahead of the game's AI.</p>\n\n<h2>Mobile Friendliness and School/Work Break Suitability</h2>\n\n<p>The <strong>bouncy basketball unblock game</strong> is fully optimized for mobile devices, allowing players to enjoy the game on-the-go. The game's intuitive controls and responsive design make it perfect for short breaks at school or work, providing a fun and engaging way to recharge and refocus.</p>\n\n<p>The game's no-install convenience also makes it an ideal choice for players who prefer not to download or install games on their devices. With the <strong>bouncy basketball unblock game</strong>, players can simply access the game through their web browser and start playing immediately.</p>\n\n<h2>Comparison Table: Bouncy Basketball vs Similar Browser Games</h2>\n\n<table>\n  <thead>\n    <tr>\n      <th>Game</th>\n      <th>Pace</th>\n      <th>Skill Ceiling</th>\n      <th>Session Length</th>\n      <th>Accessibility</th>\n    </tr>\n  </thead>\n  <tbody>\n    <tr>\n      <td>Bouncy Basketball</td>\n      <td>Medium</td>\n      <td>High</td>\n      <td>5-10 minutes</td>\n      <td>Easy</td>\n    </tr>\n    <tr>\n      <td>Angry Birds</td>\n      <td>Fast</td>\n      <td>Medium</td>\n      <td>2-5 minutes</td>\n      <td>Easy</td>\n    </tr>\n    <tr>\n      <td>Pool Live Tour</td>\n      <td>Slow</td>\n      <td>High</td>\n      <td>10-20 minutes</td>\n      <td>Medium</td>\n    </tr>\n    <tr>\n      <td>Agar.io</td>\n      <td>Fast</td>\n      <td>Medium</td>\n      <td>2-5 minutes</td>\n      <td>Easy</td>\n    </tr>\n  </tbody>\n</table>\n\n<h2>Pros and Cons of the Bouncy Basketball Unblock Game</h2>\n\n<ul>\n  <li><strong>Pros:</strong>\n    <ul>\n      <li>High replay value due to procedurally generated levels</li>\n      <li>Increasing difficulty and challenge</li>\n      <li>Intuitive controls and smooth animations</li>\n      <li>Mobile friendly and no-install convenience</li>\n    </ul>\n  </li>\n  <li><strong>Cons:</strong>\n    <ul>\n      <li>Some players may find the game too challenging or frustrating</li>\n      <li>The game's AI can be aggressive and unpredictable</li>\n    </ul>\n  </li>\n</ul>",
    "questions": [
        {
            "question": "What is bouncy basketball and what should new players focus on?",
            "answer": "bouncy basketball is a browser sports game where timing and decision-making matter most. Learn the basic mechanics first, then optimize tactics."
        },
        {
            "question": "How can I win more consistently in bouncy basketball?",
            "answer": "Focus on fundamentals like positioning, tempo, and clean execution. Consistent simple plays usually beat risky highlight attempts."
        },
        {
            "question": "Why do I make repeated mistakes in bouncy basketball?",
            "answer": "Repeated mistakes often come from rushed decisions under pressure. Slow down key moments and play around your strongest patterns."
        },
        {
            "question": "What are the best tips for competitive matches in bouncy basketball?",
            "answer": "Adapt your approach based on momentum and opponent behavior. Small tactical adjustments during a match can decide close results."
        },
        {
            "question": "Can I play bouncy basketball casually in short sessions?",
            "answer": "Yes, most sports browser games work well in quick sessions. Use short practice rounds to sharpen one skill at a time."
        },
        {
            "question": "Are there similar sports games to bouncy basketball?",
            "answer": "Yes, try titles with similar pace and control style. Rotating between comparable games helps improve reaction and tactical reading."
        },
        {
            "question": "Can I play bouncy basketball on mobile devices?",
            "answer": "In most cases, bouncy basketball runs on modern mobile browsers, but controls can feel different from desktop. Use landscape mode and a stable connection for better responsiveness."
        },
        {
            "question": "Is bouncy basketball unblock game free to play?",
            "answer": "Yes, browser games like this are usually free and do not require installation. Open the game page directly and start playing after it finishes loading."
        },
        {
            "question": "What should I do if bouncy basketball is laggy or not loading?",
            "answer": "Refresh the page, close unused tabs, and switch to a stable network. If the issue continues, try another browser and disable heavy extensions."
        },
        {
            "question": "Is bouncy basketball suitable for short breaks at school or work?",
            "answer": "Yes, most sessions are short and quick to start, so it is suitable for short breaks. Play in smaller sessions and pause between runs to stay consistent."
        }
    ],
    "related_keywords": [
        "bouncy basketball unblocked game",
        "bouncy basketball online browser game",
        "bouncy basketball no download free",
        "tips for playing bouncy basketball",
        "bouncy basketball controls explained",
        "how to play bouncy basketball mobile",
        "bouncy basketball strategy guide",
        "similar games to bouncy basketball",
        "bouncy basketball unblocked games 66",
        "bouncy basketball online no download",
        "bouncy basketball browser game no flash",
        "bouncy basketball mobile game download",
        "bouncy basketball game tips and tricks",
        "bouncy basketball controls on mobile",
        "best strategy to play bouncy basketball",
        "bouncy basketball online game free no download",
        "how to beat level in bouncy basketball",
        "bouncy basketball unblocked free online",
        "bouncy basketball browser game online",
        "bouncy basketball mobile game tips and tricks"
    ]
}
