{
    "title": "Vex 8",
    "title_blog": "Mastering Vex 8 Unblock Game: Tips and Tricks to Beat Levels Fast",
    "meta_description": "\"Unblock Vex 8 online in your browser, challenge yourself in this addictive puzzle game with increasingly complex levels and obstacles.\"",
    "meta_description_blog": "\"Unlock new levels in Vex 8 with expert tips and strategies. Master the unblock game and beat the highest scores.\"",
    "description": "<strong>vex 8 unblock game<\/strong> enthusiasts, rejoice! You've stumbled upon the ultimate guide to mastering this addictive browser game. In this article, we'll dive into the world of Vex 8, exploring its core gameplay loop, controls, tips, and tricks to help you overcome the obstacles and reach the ultimate goal.\n\n<h2>Core Gameplay Loop and Win Condition<\/h2>\n<p>Vex 8 is a challenging platformer that requires precision and timing. Your goal is to guide a small robot through increasingly complex levels, avoiding obstacles and enemies while collecting power-ups and bonuses. The game features a unique mechanic where the robot can move in any direction, including diagonally, adding a new layer of complexity to the gameplay.<\/p>\n<p>The win condition is simple: reach the end of each level without dying. Sounds easy, right? Think again. As you progress through the game, the levels become increasingly difficult, with tighter spaces, faster enemies, and more complex obstacles.<\/p>\n<p>The game features a variety of levels, each with its unique challenges and requirements. You'll need to adapt your strategy and reflexes to overcome the obstacles and reach the end.<\/p>\n\n<h2>Controls and Desktop\/Mobile Touch Adaptation<\/h2>\n<p>The controls in Vex 8 are intuitive and easy to learn. On desktop, you can use the arrow keys or WASD keys to control the robot's movement. On mobile devices, you can use touch controls to navigate the robot.<\/p>\n<p>The game features a responsive design that adapts to different screen sizes and devices. Whether you're playing on a desktop, laptop, or mobile device, the game will adjust its controls and layout to provide an optimal gaming experience.<\/p>\n<p>One of the unique features of Vex 8 is its use of gestures on mobile devices. You can use swipes, taps, and holds to control the robot's movement, adding a new layer of complexity and challenge to the gameplay.<\/p>\n\n<h2>Beginner and Intermediate Tips<\/h2>\n<p>As a beginner, it's essential to start with the easier levels and gradually increase the difficulty as you become more comfortable with the gameplay. Here are a few tips to get you started:<\/p>\n<ul>\n<li>Start with the default controls and adjust them to your liking.<\/li>\n<li>Practice, practice, practice! The more you play, the better you'll become.<\/li>\n<li>Use the power-ups and bonuses to your advantage. They can help you overcome obstacles and reach the end of the level.<\/li>\n<li>Pay attention to the robot's movement and adjust your strategy accordingly.<\/li>\n<\/ul>\n\n<h2>Performance\/Browser Compatibility and Quick-Load\/No-Download Value<\/h2>\n<p>Vex 8 is a browser-based game that runs smoothly on most modern browsers, including Google Chrome, Mozilla Firefox, and Microsoft Edge. The game is optimized for low-end devices, making it accessible to a wide range of players.<\/p>\n<p>The game loads quickly, with no downloads required. Simply click the play button, and you'll be ready to start playing in seconds.<\/p>\n<p>Vex 8 is an excellent choice for players who want to play games online without the hassle of downloads or installations.<\/p>\n\n<h2>Who is Vex 8 Best For?<\/h2>\n<p>Vex 8 is best suited for players who enjoy challenging platformers with a unique twist. The game requires precision, timing, and strategy, making it an excellent choice for players who enjoy puzzle games and brain teasers.<\/p>\n<p>The game is also suitable for players of all ages, from kids to adults. The gameplay is simple to learn, but challenging to master, making it an excellent choice for players of all skill levels.<\/p>\n\n<h2>Common Mistakes and Strategies<\/h2>\n<p>Here's a table comparing different modes, difficulties, recommended strategies, and common mistakes:<\/p>\n<table>\n  <thead>\n    <tr>\n      <th>Mode<\/th>\n      <th>Difficulty<\/th>\n      <th>Recommended Strategy<\/th>\n      <th>Common Mistakes<\/th>\n    <\/tr>\n  <\/thead>\n  <tbody>\n    <tr>\n      <td>Time Attack<\/td>\n      <td>Hard<\/td>\n      <td>Focus on speed and precision.<\/td>\n      <td>Misjudging the robot's movement.<\/td>\n    <\/tr>\n    <tr>\n      <td>Endless<\/td>\n      <td>Medium<\/td>\n      <td>Focus on survival and adaptation.<\/td>\n      <td>Not paying attention to the environment.<\/td>\n    <\/tr>\n    <tr>\n      <td>Challenge<\/td>\n      <td>Easy<\/td>\n      <td>Focus on exploration and discovery.<\/td>\n      <td>Not exploring the level thoroughly.<\/td>\n    <\/tr>\n  <\/tbody>\n<\/table>\n\n<h2>Why Play Vex 8 Unblocked?<\/h2>\n<p>Vex 8 is an excellent choice for players who want to play a challenging and addictive platformer without the hassle of downloads or installations. The game is optimized for low-end devices, making it accessible to a wide range of players.<\/p>\n<p>The game's unique mechanic, responsive design, and quick-load value make it an excellent choice for players who want to play games online without the hassle of downloads or installations.<\/p>\n<p>So, what are you waiting for? Start playing Vex 8 unblocked today and experience the thrill of this addictive browser game!<\/p>",
    "description_alt": "<h2>Mastering the Vex 8 Unblock Game: Tips and Strategies<\/h2>\n\n<p>The <strong>vex 8 unblock game<\/strong> has taken the browser gaming world by storm, captivating players with its addictive gameplay and increasing difficulty curve. If you're looking for a challenge that will keep you engaged for hours on end, look no further. In this article, we'll delve into the world of Vex 8, exploring what makes it replayable, common player mistakes, and strategies for progression.<\/p>\n\n<h2>Replayability and Difficulty Spikes<\/h2>\n\n<p>One of the key factors that sets Vex 8 apart from other browser games is its high replayability factor. As you progress through the levels, the game's AI adapts to your playing style, ensuring that each subsequent run is a new challenge. Difficulty spikes occur around level 20-30, where the game introduces new obstacles and enemies that require a higher level of skill and strategy to overcome.<\/p>\n\n<p>However, this increased difficulty is not a deterrent, but rather an opportunity for players to improve their skills and master the game. By analyzing your mistakes and adapting your strategy, you can overcome even the toughest challenges and reach new heights in the game.<\/p>\n\n<h2>Common Player Mistakes and How to Fix Them<\/h2>\n\n<p>As with any game, there are common mistakes that players make when starting out. One of the most common mistakes is rushing through levels without taking the time to learn the game's mechanics and patterns. This can lead to frustration and a high likelihood of failure.<\/p>\n\n<p>Another mistake is not paying attention to the game's visual cues, such as the red dots that indicate enemy positions. By ignoring these cues, players can easily get caught off guard and lose a life. To fix these mistakes, players should take their time to learn the game's mechanics and patterns, and pay close attention to the game's visual cues.<\/p>\n\n<h2>Strategy Progression: From Basics to Mastery<\/h2>\n\n<p>When starting out, players should focus on learning the game's basic mechanics, such as movement and jumping. As you progress through the levels, you'll encounter new obstacles and enemies that require a higher level of skill and strategy to overcome.<\/p>\n\n<p>Once you've mastered the basics, it's time to move on to more advanced strategies, such as using the environment to your advantage and exploiting enemy weaknesses. With practice and patience, you'll be able to overcome even the toughest challenges and reach new heights in the game.<\/p>\n\n<h2>Mobile Friendliness and School\/Work Break Suitability<\/h2>\n\n<p>Vex 8 is fully optimized for mobile devices, making it the perfect game to play during your daily commute or school\/work breaks. The game's intuitive controls and fast-paced action make it easy to pick up and play, even in short sessions.<\/p>\n\n<p>Whether you're on a bus, train, or just need a quick break at work, Vex 8 is the perfect game to keep you entertained and engaged. With its no-install convenience and browser-based gameplay, you can play anywhere, anytime.<\/p>\n\n<h2>Pros and Cons of Playing Vex 8<\/h2>\n\n<ul>\n  <li>High replayability factor, with increasing difficulty and new challenges<\/li>\n  <li>Easy to learn, but difficult to master, with a high skill ceiling<\/li>\n  <li>Mobile-friendly and suitable for short sessions<\/li>\n  <li>No-install convenience and browser-based gameplay<\/li>\n  <li>Can be frustrating at times, especially for new players<\/li>\n  <li>May not be suitable for young children due to challenging gameplay<\/li>\n<\/ul>\n\n<h2>Comparison with Similar Browser Games<\/h2>\n\n<table>\n  <thead>\n    <tr>\n      <th>Game<\/th>\n      <th>Pace<\/th>\n      <th>Skill Ceiling<\/th>\n      <th>Session Length<\/th>\n      <th>Accessibility<\/th>\n    <\/tr>\n  <\/thead>\n  <tbody>\n    <tr>\n      <td>Vex 8<\/td>\n      <td>Fast-paced<\/td>\n      <td>High<\/td>\n      <td>Short to medium<\/td>\n      <td>Easy<\/td>\n    <\/tr>\n    <tr>\n      <td>Agar.io<\/td>\n      <td>Medium-paced<\/td>\n      <td>Medium<\/td>\n      <td>Medium to long<\/td>\n      <td>Easy<\/td>\n    <\/tr>\n    <tr>\n      <td>Slither.io<\/td>\n      <td>Slow-paced<\/td>\n      <td>Low<\/td>\n      <td>Short to medium<\/td>\n      <td>Easy<\/td>\n    <\/tr>\n    <tr>\n      <td>Diep.io<\/td>\n      <td>Medium-paced<\/td>\n      <td>High<\/td>\n      <td>Medium to long<\/td>\n      <td>Medium<\/td>\n    <\/tr>\n  <\/tbody>\n<\/table>\n\n<h2>How to Play Vex 8: Tips and Tricks<\/h2>\n\n<p>For those looking to improve their skills and master the game, here are some additional tips and tricks to get you started:<\/p>\n\n<p>1. Learn the game's mechanics and patterns by playing through the levels slowly.<\/p>\n\n<p>2. Pay close attention to the game's visual cues, such as the red dots that indicate enemy positions.<\/p>\n\n<p>3. Use the environment to your advantage, such as by jumping on platforms or using obstacles to block enemy attacks.<\/p>\n\n<p>4. Experiment with different strategies and techniques to find what works best for you.<\/p>\n\n<p>5. Don't be afraid to die – it's all part of the learning process!<\/p>\n\n<p>By following these tips and strategies, you'll be well on your way to becoming a Vex 8 master and taking on the toughest challenges the game has to offer.<\/p>",
    "questions": [
        {
            "question": "What is the objective of Vex 8?",
            "answer": "The goal of Vex 8 is to navigate a robotic ball through a series of increasingly challenging levels by tilting the screen to control its trajectory."
        },
        {
            "question": "How do I control the robotic ball in Vex 8?",
            "answer": "You control the ball by tilting your device left or right, allowing it to roll and change direction accordingly."
        },
        {
            "question": "Is Vex 8 easy to play?",
            "answer": "No, Vex 8 is a challenging game that requires precision and timing to navigate the ball through tight spaces and obstacles."
        },
        {
            "question": "Can I play Vex 8 on my mobile device?",
            "answer": "Yes, Vex 8 is available on both iOS and Android devices, making it easily accessible on the go."
        },
        {
            "question": "Can I play Vex 8 without downloading it?",
            "answer": "Yes, you can play Vex 8 directly in your web browser without needing to download any software or apps."
        },
        {
            "question": "Is Vex 8 safe to play?",
            "answer": "Vex 8 is a safe and ad-free game that can be played without worrying about malware or other online threats."
        },
        {
            "question": "Why can't I play Vex 8 at school?",
            "answer": "Some schools may block Vex 8 due to its online nature, but you can try playing the unblocked version to access the game."
        },
        {
            "question": "How do I troubleshoot issues with Vex 8?",
            "answer": "If you're experiencing issues with Vex 8, try clearing your browser cache or checking your internet connection to ensure it's stable."
        },
        {
            "question": "Can I play Vex 8 on a desktop computer?",
            "answer": "While Vex 8 is designed for mobile devices, you can also play it on a desktop computer using a compatible web browser."
        },
        {
            "question": "How do I unlock new levels in Vex 8?",
            "answer": "You can unlock new levels in Vex 8 by progressing through the game and achieving high scores, which will grant you access to increasingly challenging levels."
        }
    ],
    "related_keywords": [
        "vex 8 unblocked game",
        "play vex 8 online",
        "vex 8 browser game",
        "no download vex 8",
        "vex 8 tips and tricks",
        "vex 8 controls explained",
        "vex 8 mobile game",
        "best strategy for vex 8",
        "similar games to vex 8",
        "vex 8 online free",
        "how to play vex 8",
        "vex 8 game download",
        "vex 8 walkthrough tutorial",
        "vex 8 level guide",
        "vex 8 game tips",
        "vex 8 unblocked online",
        "vex 8 browser games",
        "vex 8 mobile strategy",
        "vex 8 online level",
        "vex 8 game online"
    ]
}