{
    "title": "Foot Chinko",
    "title_blog": "How to Win at Foot Chinko Unblock Game",
    "meta_description": "Play Foot Chinko unblock game now in your browser, no download required, and challenge your reflexes with this addictive physics puzzle game.",
    "meta_description_blog": "\"Boost your high scores in the addictive Foot Chinko unblock game with expert tips and strategies for success.\"",
    "description": "<strong>Get Ready to Jump into the Addictive World of <strong>Foot Chinko Unblock Game<\/strong>!<\/strong>\n\nLooking for a fun and easy-to-play browser game to pass the time? Look no further than <strong>Foot Chinko<\/strong>, the popular online game that's free from downloads and accessible anywhere. With its simple controls and addictive gameplay, <strong>Foot Chinko unblock game<\/strong> is perfect for players of all ages and skill levels.\n\n<h2>Core Gameplay Loop and Win Condition<\/h2>\n<p>At its core, <strong>Foot Chinko<\/strong> is a timing-based game where players control a character who must jump and kick a chinko (a.k.a. a small, spherical object) to score points. The game is won by reaching a set score or completing a certain number of levels.<\/p>\n<p>Players must time their jumps and kicks perfectly to hit the chinko, which is moving at a steady pace down the screen. With each successful hit, the score increases, and the player progresses to the next level. The game's simplicity belies its depth, requiring players to develop a sense of timing and spatial awareness to succeed.<\/p>\n<p>As players progress, the game introduces new challenges, such as obstacles and power-ups, which require even greater precision and strategy to overcome.<\/p>\n\n<h2>Controls and Gameplay Experience<\/h2>\n<p>Playing <strong>Foot Chinko<\/strong> on desktop is straightforward: simply use the mouse to click on the screen to jump and kick the chinko. The game responds well to mouse movements, making it easy to time your actions accurately.<\/p>\n<p>On mobile devices, the touch controls are similarly intuitive, with a single tap on the screen jumping the character and a swipe gesture kicking the chinko. While mobile controls may take some getting used to, they work well for players who prefer to play on-the-go.<\/p>\n<p>Whether on desktop or mobile, <strong>Foot Chinko<\/strong> is designed to be easy to pick up and play, making it perfect for players who want a quick, stress-free gaming experience.<\/p>\n\n<h2>Performance and Browser Compatibility<\/h2>\n<p>One of the standout features of <strong>Foot Chinko<\/strong> is its excellent performance, which ensures a smooth gaming experience even on lower-end devices. The game's browser-based design means that it can be played without downloads or plugins, making it accessible to players with limited storage space or security restrictions.<\/p>\n<p>Additionally, <strong>Foot Chinko<\/strong> is optimized for a wide range of browsers, including Google Chrome, Mozilla Firefox, and Safari. This means that players can access the game from their favorite browser, without worrying about compatibility issues.<\/p>\n<p>Whether you're playing on a desktop or mobile device, <strong>Foot Chinko<\/strong> is designed to provide a seamless gaming experience that's free from lag and interruptions.<\/p>\n\n<h2>Tips and Strategies for Beginners and Intermediate Players<\/h2>\n<p>For beginners, the key to improving is to focus on timing. Practice jumping and kicking the chinko in sync to build your sense of timing and coordination.<\/p>\n<p>Intermediate players can try to focus on aiming for specific areas of the screen to maximize their score. For example, aiming for the chinko when it's in the center of the screen will result in a higher score than hitting it when it's near the edges.<\/p>\n<p>Additionally, keep an eye out for power-ups, which can greatly boost your score or provide temporary invincibility.<\/p>\n\n<h2>Common Mistakes to Avoid<\/h2>\n<ol>\n  <li>Overestimating the chinko's movement speed<\/li>\n  <li>Not adjusting to the game's increasing difficulty<\/li>\n  <li>Ignoring power-ups and obstacles<\/li>\n<\/ol>\n\n<h2>Who is <strong>Foot Chinko<\/strong> Best For?<\/h2>\n<p>Whether you're a seasoned gamer or a casual player, <strong>Foot Chinko<\/strong> is a great choice for anyone looking for a fun and easy-to-play browser game. Its simple controls and addictive gameplay make it perfect for players of all ages and skill levels.<\/p>\n<p>Additionally, the game's browser-based design and unblocked access make it a great option for players who want to play without downloads or security restrictions.<\/p>\n\n<h2>Comparison of Game Modes<\/h2>\n<table>\n  <thead>\n    <tr>\n      <th>Mode<\/th>\n      <th>Difficulty<\/th>\n      <th>Recommended Strategy<\/th>\n      <th>Common Mistakes to Avoid<\/th>\n    <\/tr>\n  <\/thead>\n  <tbody>\n    <tr>\n      <td>Time Attack<\/td>\n      <td>High<\/td>\n      <td>Focus on perfect timing and quick reflexes.<\/td>\n      <td>Don't get caught up in the excitement and lose focus.<\/td>\n    <\/tr>\n    <tr>\n      <td>Endless<\/td>\n      <td>Medium<\/td>\n      <td>Develop a sense of timing and spatial awareness.<\/td>\n      <td>Don't ignore obstacles and power-ups.<\/td>\n    <\/tr>\n    <tr>\n      <td>Challenges<\/td>\n      <td>Low<\/td>\n      <td>Take your time and focus on accuracy.<\/td>\n      <td>Don't get discouraged by initial failures.<\/td>\n    <\/tr>\n  <\/tbody>\n<\/table>\n\n<h2>Play <strong>Foot Chinko<\/strong> Online and Experience the Fun for Yourself!<\/h2>\n<p>With its simple controls, addictive gameplay, and browser-based design, <strong>Foot Chinko<\/strong> is a great choice for players of all ages and skill levels. Try it out today and experience the fun for yourself!<\/p>",
    "description_alt": "<h2>Unlock Endless Fun with <strong>Foot Chinko Unblock Game<\/strong><\/h2>\n<p>Get ready to kick your stress away with the addictive <strong>foot chinko unblock game<\/strong>! This mesmerizing browser game offers an unparalleled blend of simplicity and depth, making it a perfect fit for short breaks at school or work. With no installation required, you can dive into the world of <strong>foot chinko<\/strong> anytime, anywhere.<\/p>\n<p>What sets <strong>foot chinko unblock game<\/strong> apart from other browser games is its unique blend of rhythm and reaction time. The game's intuitive controls and increasing difficulty curve keep you engaged for hours on end, making it an ideal choice for those seeking a fun distraction during their daily routine.<\/p>\n\n<h2>Replayability and Difficulty Spikes<\/h2>\n<p>One of the key factors that contribute to the game's replayability is the unpredictable pattern of <strong>foot chinko<\/strong> blocks. As you progress, the game introduces new obstacles and speed boosts, causing difficulty spikes that will put your reflexes to the test. To overcome these challenges, you'll need to develop your timing and reaction skills, making each playthrough a unique experience.<\/p>\n<p>The game's design ensures that you'll encounter a mix of easy and hard levels, keeping you motivated to improve your performance. By mastering the basics, you'll unlock new strategies and techniques, allowing you to tackle even the most demanding levels with confidence.<\/p>\n\n<h2>Common Player Mistakes and How to Fix Them<\/h2>\n<p>Many players fall into common pitfalls, such as getting too comfortable with short rebounds or neglecting to use the correct timing. To avoid these mistakes, focus on developing a consistent rebound pattern and practice your timing by playing at different speeds.<\/p>\n<p>Another crucial aspect is learning to adapt to changing circumstances. As the game progresses, new obstacles will be introduced, requiring you to adjust your strategy on the fly. By staying focused and adapting to the situation, you'll be able to overcome even the toughest challenges.<\/p>\n\n<h2>Strategy Progression: From Beginners to Masters<\/h2>\n<p>During the first 10 minutes of playing <strong>foot chinko unblock game<\/strong>, focus on mastering the basic controls and getting a feel for the game's rhythm. As you progress, you'll start to develop more complex strategies, such as using speed boosts to your advantage and learning to navigate through tight spaces.<\/p>\n<p>Once you've reached the mastery phase, you'll be able to execute intricate combos and navigate through even the most challenging levels with ease. This is where the game truly shines, offering a sense of accomplishment and satisfaction that's hard to find in other browser games.<\/p>\n\n<h2>Mobile Friendliness and School\/Work Break Suitability<\/h2>\n<p>One of the standout features of <strong>foot chinko unblock game<\/strong> is its seamless mobile experience. Whether you're playing on a smartphone or tablet, the game's controls and design are perfectly optimized for on-the-go fun.<\/p>\n<p>With short sessions that can be completed in just a few minutes, <strong>foot chinko unblock game<\/strong> is an ideal choice for school or work breaks. Its calming atmosphere and addictive gameplay make it the perfect way to relax and recharge during your daily routine.<\/p>\n\n<h2>Comparison Table: Foot Chinko vs Similar Browser Games<\/h2>\n<table>\n\t<thead>\n\t\t<tr>\n\t\t\t<th><\/th>\n\t\t\t<th>Foot Chinko<\/th>\n\t\t\t<th>Similar Browser Games<\/th>\n\t\t<\/tr>\n\t<\/thead>\n\t<tbody>\n\t\t<tr>\n\t\t\t<td>Pace<\/td>\n\t\t\t<td>Fast-paced, increasing difficulty<\/td>\n\t\t\t<td>Slow-paced, repetitive gameplay<\/td>\n\t\t<\/tr>\n\t\t<tr>\n\t\t\t<td>Skill Ceiling<\/td>\n\t\t\t<td>High, requiring precise timing and reaction<\/td>\n\t\t\t<td>Low, relying on luck and basic reflexes<\/td>\n\t\t<\/tr>\n\t\t<tr>\n\t\t\t<td>Session Length<\/td>\n\t\t\t<td>Short, 5-10 minutes<\/td>\n\t\t\t<td>Long, 15-30 minutes<\/td>\n\t\t<\/tr>\n\t\t<tr>\n\t\t\t<td>Accessibility<\/td>\n\t\t\t<td>High, playable on any device with a browser<\/td>\n\t\t\t<td>Low, requiring specific software or plugins<\/td>\n\t\t<\/tr>\n\t<\/tbody>\n<\/table>\n\n<h2>Pros and Cons of Playing Foot Chinko<\/h2>\n<ul>\n\t<li><strong>Pros:<\/strong>\n\t\t<ul>\n\t\t\t<li>High replayability and difficulty spikes<\/li>\n\t\t\t<li>Intuitive controls and increasing challenge<\/li>\n\t\t\t<li>Seamless mobile experience and short session length<\/li>\n\t\t<\/ul>\n\t<\/li>\n\t<li><strong>Cons:<\/strong>\n\t\t<ul>\n\t\t\t<li>High skill ceiling may deter casual players<\/li>\n\t\t\t<li>Unpredictable pattern of <strong>foot chinko<\/strong> blocks may lead to frustration<\/li>\n\t\t<\/ul>\n\t<\/li>\n<\/ul>",
    "questions": [
        {
            "question": "How do I play Foot Chinko unblock game on my computer?",
            "answer": "To play, use your mouse to control the player's movements and jump. Click on the screen to jump or change direction. Simply navigate the player through obstacles without losing a life."
        },
        {
            "question": "What are the controls for Foot Chinko game on mobile devices?",
            "answer": "On mobile devices, swipe left or right to move the player and tap the screen to jump. You can also use on-screen buttons to control the player's movements."
        },
        {
            "question": "Is Foot Chinko game easy or hard to play?",
            "answer": "Foot Chinko is a challenging game that requires quick reflexes and precise timing. As you progress, the obstacles and difficulty level increase, making it harder to complete levels."
        },
        {
            "question": "Is Foot Chinko unblock game available on mobile phones?",
            "answer": "Yes, Foot Chinko can be played on most mobile phones, including Android and iOS devices. Simply visit the game's website and click on the 'Play' button to start playing."
        },
        {
            "question": "Why can't I access Foot Chinko unblock game on my school computer?",
            "answer": "School computers often have strict security settings that block access to certain websites, including those that may contain unblocked games. Try accessing the game from a different device or using a VPN to bypass restrictions."
        },
        {
            "question": "Is Foot Chinko game safe to play?",
            "answer": "Foot Chinko is a safe and ad-free game that does not collect any personal data or require users to create an account. You can play without worrying about malware or other online threats."
        },
        {
            "question": "How do I fix Foot Chinko game not loading on my browser?",
            "answer": "Try clearing your browser's cache and cookies or checking that your internet connection is stable. If the issue persists, try using a different browser or updating your browser to the latest version."
        },
        {
            "question": "Can I play Foot Chinko unblock game on my tablet?",
            "answer": "Yes, Foot Chinko is compatible with most tablets, including those running on Android and iOS. Simply visit the game's website and start playing in your tablet's web browser."
        },
        {
            "question": "Why does Foot Chinko game keep crashing on my computer?",
            "answer": "Foot Chinko may crash if your computer's graphics card or browser is not capable of handling the game's demands. Try updating your graphics card drivers or using a different browser to resolve the issue."
        }
    ],
    "related_keywords": [
        "foot chinko unblocked game",
        "play foot chinko online",
        "foot chinko no download",
        "foot chinko browser game",
        "foot chinko unblocked games",
        "foot chinko tips and tricks",
        "foot chinko controls explained",
        "foot chinko mobile game",
        "strategy for foot chinko",
        "foot chinko similar games",
        "foot chinko unblocked version",
        "foot chinko online multiplayer",
        "free foot chinko game",
        "foot chinko no ads",
        "how to play foot chinko",
        "foot chinko game online free",
        "foot chinko browser based game",
        "foot chinko unblocked at school",
        "foot chinko strategy guide",
        "foot chinko online version"
    ]
}