{
    "title": "Freeway Fury",
    "title_blog": "Unlock the Secrets of Freeway Fury Unblocked Game",
    "meta_description": "\"Get ready for a crazy racing experience on the high-speed freeway. Play Freeway Fury unblock game right in your browser, no download required, and speed through traffic like never before.\"",
    "meta_description_blog": "\"Unlock ultimate speed in Freeway Fury unblock game with expert tips and strategies to dominate the road and crush your opponents.\"",
    "description": "<strong>Freeway Fury Unblock Game<\/strong> is a thrilling racing game that has captured the hearts of many gamers worldwide. This addictive browser-based game offers an unparalleled experience, allowing players to enjoy high-speed racing without the need for downloading or installing any software. With its intuitive controls and exciting gameplay, Freeway Fury is a must-play for anyone looking to indulge in a quick, fun, and challenging online gaming experience.\n\n<h2>Core Gameplay Loop and Win Condition<\/h2>\n<p>At its core, Freeway Fury is a high-speed racing game where players control a vehicle, navigating through a busy highway filled with obstacles and challenges. The objective is to reach the end of the track as quickly as possible, while avoiding collisions with other vehicles, pedestrians, and road hazards. The game features multiple modes, including Time Trial, where players aim to beat their previous lap times, and Survival Mode, where the goal is to survive as long as possible.<\/p>\n<p>As players progress through the game, they will encounter various obstacles, such as traffic cones, construction zones, and even challenges like oil slicks and potholes. The game requires quick reflexes and sharp timing to navigate these obstacles successfully. The win condition is simple: reach the end of the track in the shortest time possible.<\/p>\n<p>Throughout the game, players will earn points and rewards for completing laps, completing challenges, and achieving specific milestones. These rewards can be used to unlock new vehicles, upgrade existing ones, or access special power-ups.<\/p>\n\n<h2>Controls and Gameplay Mechanics<\/h2>\n<p>Freeway Fury features intuitive controls that make it easy for players to navigate the game. On desktop, players use the keyboard to control the vehicle, using the arrow keys to steer and accelerate. The game also supports mobile touch controls, allowing players to tap and swipe their way through the game on their tablets or smartphones.<\/p>\n<p>The game mechanics are designed to be responsive and easy to learn, making it accessible to players of all ages and skill levels. Players can adjust the game speed and difficulty level to suit their preferences, ensuring an enjoyable experience for everyone.<\/p>\n<p>One of the standout features of Freeway Fury is its <strong>responsive controls<\/strong>. The game's developers have implemented a robust physics engine, allowing for realistic vehicle behavior and precise control. This makes the game feel immersive and engaging, even at high speeds.<\/p>\n\n<h2>Performance, Browser Compatibility, and Quick-Load Value<\/h2>\n<p>Freeway Fury is designed to run smoothly on a wide range of devices, including desktops, laptops, tablets, and smartphones. The game is built using HTML5 and JavaScript, making it compatible with most modern web browsers, including Google Chrome, Mozilla Firefox, Safari, and Microsoft Edge.<\/p>\n<p>The game loads quickly, even on slower internet connections, and requires no download or installation process. This makes it perfect for playing on-the-go or during short breaks at work or school.<\/p>\n<p>One of the significant advantages of playing Freeway Fury in a browser is its <strong>cross-platform compatibility<\/strong>. Players can access the game from any device with a modern web browser, making it a great option for gamers who prefer to play on multiple devices.<\/p>\n\n<h2>Beginner and Intermediate Tips<\/h2>\n<p>For beginners, here are a few tips to get you started:<\/p>\n<ul>\n\t<li>Start with the default vehicle and adjust the difficulty level to suit your preferences.<\/li>\n\t<li>Focus on navigating the track, rather than trying to perform fancy stunts.<\/li>\n\t<li>Use the game's built-in controls to adjust the vehicle's speed and acceleration.<\/li>\n<\/ul>\n<p>For intermediate players, here are a few tips to improve your performance:<\/p>\n<ul>\n\t<li>Experiment with different vehicle upgrades and power-ups to find the ones that work best for you.<\/li>\n\t<li>Practice your timing and reflexes to improve your lap times.<\/li>\n\t<li>Focus on avoiding obstacles and using the game's terrain to your advantage.<\/li>\n<\/ul>\n\n<h2>Who is Freeway Fury Best For?<\/h2>\n<p>Freeway Fury is an excellent choice for anyone looking for a fun, fast-paced racing game that can be played online. It's perfect for:<\/p>\n<ul>\n\t<li>Casual gamers who want to relax and have fun.<\/li>\n\t<li>Competitive players who want to challenge themselves and improve their skills.<\/li>\n\t<li>Gamers who prefer to play on multiple devices or don't want to download software.<\/li>\n<\/ul>\n\n<h2>Table Comparison of Freeway Fury Modes<\/h2>\n<table>\n\t<thead>\n\t\t<tr>\n\t\t\t<th>Mode<\/th>\n\t\t\t<th>Difficulty Level<\/th>\n\t\t\t<th>Recommended Strategy<\/th>\n\t\t\t<th>Common Mistakes<\/th>\n\t\t<\/tr>\n\t<\/thead>\n\t<tbody>\n\t\t<tr>\n\t\t\t<td>Time Trial<\/td>\n\t\t\t<td>Medium<\/td>\n\t\t\t<td>Concentrate on beating your previous lap times.<\/td>\n\t\t\t<td>Don't get distracted by obstacles and focus on the track.<\/td>\n\t\t<\/tr>\n\t\t<tr>\n\t\t\t<td>Survival Mode<\/td>\n\t\t\t<td>Hard<\/td>\n\t\t\t<td>Conserve fuel and avoid collisions at all costs.<\/td>\n\t\t\t<td>Don't underestimate the difficulty of the mode; it's much harder than it looks.<\/td>\n\t\t<\/tr>\n\t\t<tr>\n\t\t\t<td>Challenge Mode<\/td>\n\t\t\t<td>Easy<\/td>\n\t\t\t<td>Focus on completing challenges and earning rewards.<\/td>\n\t\t\t<td>Don't get too comfortable; the challenges will get progressively harder.<\/td>\n\t\t<\/tr>\n\t\t<tr>\n\t\t\t<td>Multiplayer Mode<\/td>\n\t\t\t<td>Medium-Hard<\/td>\n\t\t\t<td>Focus on staying ahead of the competition and using your opponents' mistakes to your advantage.<\/td>\n\t\t\t<td>Don't get distracted by your opponents; stay focused on the track and your own performance.<\/td>\n\t\t<\/tr>\n\t<\/tbody>\n<\/table>",
    "description_alt": "<h2>Mastering the High-Speed Thrills of <strong>Freeway Fury Unblock Game<\/strong><\/h2>\n<p>Get ready to unleash your inner speed demon with <strong>Freeway Fury Unblock Game<\/strong>, the adrenaline-fueled racing game that will keep you on the edge of your seat. With its simple yet addictive gameplay, this browser-based game is perfect for players of all ages and skill levels. Whether you're looking for a quick break at school or a relaxing session at work, <strong>Freeway Fury Unblock Game<\/strong> is the perfect companion.<\/p>\n<p>But what makes this game truly replayable? The answer lies in its expertly designed level progression, which ramps up the difficulty at just the right moments. As you progress through the levels, you'll encounter increasingly challenging obstacles, including treacherous road conditions, pesky pedestrians, and rival drivers trying to knock you off course.<\/p>\n<p>So, how do you stay ahead of the competition? It all starts with mastering the basics. In the first 10 minutes of playing, focus on getting a feel for the controls and learning the optimal racing line. As you get more comfortable, you can start to experiment with different strategies, such as using your nitro boost to gain an edge or blocking off sections of the road to protect yourself from incoming traffic.<\/p>\n<h2>Common Mistakes to Avoid in <strong>Freeway Fury Unblock Game<\/strong><\/h2>\n<p>Don't let common mistakes hold you back from achieving mastery in <strong>Freeway Fury Unblock Game<\/strong>. Here are a few pitfalls to watch out for:<\/p>\n<ul>\n\t<li>Don't get too aggressive with your nitro boost – it's easy to burn out and leave yourself vulnerable to attacks.<\/li>\n\t<li>Keep an eye on your fuel level – running out of gas in the middle of a level can be disastrous.<\/li>\n\t<li>Don't underestimate the power of blocking – it's a crucial skill that can help you protect yourself from rival drivers.<\/li>\n<\/ul>\n<h2>Strategies for Success in <strong>Freeway Fury Unblock Game<\/strong><\/h2>\n<p>As you progress through the levels, you'll need to adapt your strategy to stay ahead of the competition. Here are a few tips to help you succeed:<\/p>\n<p>First, focus on building your skills in the early levels. Practice your drifting and blocking techniques, and get a feel for the optimal racing line. As you get more comfortable, you can start to experiment with different strategies, such as using your nitro boost to gain an edge or blocking off sections of the road to protect yourself from incoming traffic.<\/p>\n<p>Next, focus on mastering the art of blocking. This is a crucial skill that will help you protect yourself from rival drivers and stay ahead of the competition. Practice blocking off sections of the road and using your nitro boost to get ahead.<\/p>\n<p>Finally, focus on improving your reaction time and spatial awareness. As the levels get more challenging, you'll need to be able to react quickly to incoming traffic and obstacles. Practice your reflexes and stay focused to stay ahead of the competition.<\/p>\n<h2>How to Play <strong>Freeway Fury Unblock Game<\/strong> Like a Pro<\/h2>\n<p>Want to take your gameplay to the next level? Here are a few advanced tips to help you succeed:<\/p>\n<p>First, focus on mastering the art of timing. Learn to time your jumps and drifts perfectly to get the most out of your nitro boost. Practice your timing and stay focused to stay ahead of the competition.<\/p>\n<p>Next, focus on improving your spatial awareness. Practice navigating through tight spaces and avoiding obstacles to stay ahead of the competition.<\/p>\n<p>Finally, focus on building your skills in the later levels. Practice your drifting and blocking techniques, and get a feel for the optimal racing line. As you get more comfortable, you can start to experiment with different strategies, such as using your nitro boost to gain an edge or blocking off sections of the road to protect yourself from incoming traffic.<\/p>\n<h2><strong>Freeway Fury Unblock Game<\/strong> vs. Similar Browser Games<\/h2>\n<p>How does <strong>Freeway Fury Unblock Game<\/strong> stack up against similar browser games? Here's a comparison of some of the key features:<\/p>\n<table>\n\t<thead>\n\t\t<tr>\n\t\t\t<th>Game<\/th>\n\t\t\t<th>Pace<\/th>\n\t\t\t<th>Skill Ceiling<\/th>\n\t\t\t<th>Session Length<\/th>\n\t\t\t<th>Accessibility<\/th>\n\t\t<\/tr>\n\t<\/thead>\n\t<tbody>\n\t\t<tr>\n\t\t\t<td><strong>Freeway Fury Unblock Game<\/strong><\/td>\n\t\t\t<td>High<\/td>\n\t\t\t<td>Medium-High<\/td>\n\t\t\t<td>5-10 minutes<\/td>\n\t\t\t<td>Easy<\/td>\n\t\t<\/tr>\n\t\t<tr>\n\t\t\t<td>Madalin Stunt Cars<\/td>\n\t\t\t<td>Medium<\/td>\n\t\t\t<td>Low-Medium<\/td>\n\t\t\t<td>10-20 minutes<\/td>\n\t\t\t<td>Easy<\/td>\n\t\t<\/tr>\n\t\t<tr>\n\t\t\t<td>Super Taxi<\/td>\n\t\t\t<td>Medium-High<\/td>\n\t\t\t<td>Medium-High<\/td>\n\t\t\t<td>10-20 minutes<\/td>\n\t\t\t<td>Medium<\/td>\n\t\t<\/tr>\n\t\t<tr>\n\t\t\t<td>Racing Games 3D<\/td>\n\t\t\t<td>High<\/td>\n\t\t\t<td>High<\/td>\n\t\t\t<td>20-30 minutes<\/td>\n\t\t\t<td>Medium-Hard<\/td>\n\t\t<\/tr>\n\t<\/tbody>\n<\/table>\n<h2><strong>Freeway Fury Unblock Game<\/strong> on Mobile and at School\/Work<\/h2>\n<p>Want to play <strong>Freeway Fury Unblock Game<\/strong> on the go? The game is fully optimized for mobile devices, so you can play it anywhere, anytime. Plus, the game is completely free to play, so you can enjoy it without any in-game purchases or ads.<\/p>\n<p>And don't worry about playing at school or work – the game is completely unblocked and can be played on any device with a modern web browser. Simply visit the game's website and start playing – no downloads or installations required!<\/p>\n<h2><strong>Freeway Fury Unblock Game<\/strong> Tips and Tricks<\/h2>\n<p>Want to take your gameplay to the next level? Here are a few more tips and tricks to help you succeed:<\/p>\n<p>First, focus on improving your reaction time and spatial awareness. Practice navigating through tight spaces and avoiding obstacles to stay ahead of the competition.<\/p>\n<p>Next, focus on mastering the art of timing. Learn to time your jumps and drifts perfectly to get the most out of your nitro boost. Practice your timing and stay focused to stay ahead of the competition.<\/p>\n<p>Finally, focus on building your skills in the later levels. Practice your drifting and blocking techniques, and get a feel for the optimal racing line. As you get more comfortable, you can start to experiment with different strategies, such as using your nitro boost to gain an edge or blocking off sections of the road to protect yourself from incoming traffic.<\/p>",
    "questions": [
        {
            "question": "What is the objective of Freeway Fury unblock game?",
            "answer": "The main goal of Freeway Fury is to survive as long as possible while driving through a crowded highway. Players must avoid obstacles and collide with other vehicles to earn points. The game requires quick reflexes and good timing to navigate through the increasingly challenging levels."
        },
        {
            "question": "How do I play Freeway Fury on my mobile device?",
            "answer": "Freeway Fury can be played on mobile devices with a compatible web browser. Simply navigate to the game's website, and you can start playing without any downloads or installations. The game is optimized for touch controls, making it easy to play on-the-go."
        },
        {
            "question": "Is Freeway Fury a challenging game?",
            "answer": "Yes, Freeway Fury can be quite challenging, especially as you progress through the levels. The game requires quick reflexes and good timing to navigate through the crowded highway. However, with practice and experience, players can improve their skills and increase their chances of survival."
        },
        {
            "question": "Can I play Freeway Fury for free?",
            "answer": "Yes, Freeway Fury is available to play for free on the game's website. The game does not require any downloads or installations, and you can start playing immediately. However, some features or content may be restricted or require in-game purchases."
        },
        {
            "question": "Is Freeway Fury safe to play?",
            "answer": "Yes, Freeway Fury is a safe and secure game to play. The game is hosted on a reputable website, and it does not contain any malicious software or viruses. However, as with any online game, it's always a good idea to exercise caution and use a secure internet connection."
        },
        {
            "question": "How do I troubleshoot common issues with Freeway Fury?",
            "answer": "If you're experiencing issues with Freeway Fury, try clearing your browser's cache and cookies or updating your browser to the latest version. Additionally, check your internet connection to ensure it's stable and secure. If the issue persists, try restarting the game or contacting the game's support team for further assistance."
        },
        {
            "question": "Can I play Freeway Fury without downloading anything?",
            "answer": "Yes, Freeway Fury can be played without any downloads or installations. The game is a browser-based game that can be accessed directly from the game's website. Simply navigate to the website, and you can start playing immediately."
        },
        {
            "question": "Is Freeway Fury available on all browsers?",
            "answer": "Freeway Fury is compatible with most modern web browsers, including Google Chrome, Mozilla Firefox, and Microsoft Edge. However, some older browsers or browser versions may not be supported. If you're experiencing issues, try updating your browser to the latest version."
        },
        {
            "question": "Can I play Freeway Fury on my desktop computer?",
            "answer": "Yes, Freeway Fury can be played on desktop computers with a compatible web browser. Simply navigate to the game's website, and you can start playing on your desktop computer. The game is optimized for keyboard and mouse controls, making it easy to play with precision and accuracy."
        },
        {
            "question": "How do I unblock Freeway Fury if it's blocked by my network?",
            "answer": "If Freeway Fury is blocked by your network, try contacting your network administrator or ISP to request access to the game's website. Alternatively, you can try accessing the game through a VPN or proxy server to bypass any network restrictions."
        }
    ],
    "related_keywords": [
        "freeway fury unblocked game online",
        "freeway fury browser game no download",
        "how to play freeway fury unblocked",
        "freeway fury mobile game free",
        "freeway fury strategy game tips",
        "freeway fury unblocked game controls",
        "freeway fury online game no flash",
        "freeway fury browser game strategy",
        "freeway fury unblocked game walkthrough",
        "freeway fury similar games mobile",
        "how to win freeway fury unblocked",
        "freeway fury online game no download",
        "freeway fury browser game review",
        "freeway fury unblocked game tips and tricks",
        "freeway fury mobile game strategy guide",
        "freeway fury online game free no download",
        "freeway fury unblocked game levels",
        "freeway fury browser game hints",
        "freeway fury similar games online",
        "freeway fury unblocked game cheats"
    ]
}