{
    "title": "Infinite Soccer",
    "title_blog": "Infinite Soccer Unblock Game Tips and Tricks",
    "meta_description": "\"Embark on an endless soccer adventure with Infinite Soccer, a thrilling unblock game to play directly in your browser, no download required. Challenge your skills and score goals forever!\"",
    "meta_description_blog": "\"Master the strategy of Infinite Soccer: expert tips and tricks to unblock all levels and achieve game perfection.\"",
    "description": "<strong>Get ready to score goals and experience the ultimate thrill of <strong>infinite soccer unblock game<\/strong>!<\/strong> This browser-based game has taken the online gaming scene by storm, and for good reason. With its endless gameplay, simple controls, and addictive mechanics, <strong>infinite soccer<\/strong> is the perfect destination for anyone looking to unwind and have some fun.\n\n<h2>Gameplay and Win Condition<\/h2>\n<p>The gameplay of <strong>infinite soccer<\/strong> revolves around scoring as many goals as possible within a set time limit. The game features a simple yet intuitive control system, allowing players to control their player using the keyboard or touch controls on mobile devices.<\/p>\n<p>The game starts with a quick tutorial, teaching you the basics of movement and shooting. As you progress, the difficulty level increases, and you'll encounter various opponents with different speeds and playing styles.<\/p>\n<p>One of the unique features of <strong>infinite soccer<\/strong> is the infinite gameplay. You can play as long as you want, and the game will keep track of your score. The win condition is to score as many goals as possible, and the player with the highest score at the end of the game wins.<\/p>\n\n<h2>Controls and Gameplay<\/h2>\n<p>The controls of <strong>infinite soccer<\/strong> are simple and easy to learn, making it accessible to players of all ages and skill levels. On desktop, you can use the keyboard to control your player, using the W, A, S, and D keys to move and the space bar to shoot.<\/p>\n<p>On mobile devices, the controls are adapted for touch screens, allowing you to swipe and tap to control your player. The game also features auto-run mode, allowing you to play without having to manually control your player.<\/p>\n<p>The game also features a variety of power-ups and bonuses that can be earned and used to give you an edge over your opponents.<\/p>\n\n<h2>Performance and Browser Compatibility<\/h2>\n<p><strong>Infinite soccer unblock game<\/strong> is optimized for play in most modern web browsers, including Google Chrome, Mozilla Firefox, and Safari. The game loads quickly, with no need to download any software or plugins.<\/p>\n<p>The game is also designed to work smoothly on both desktop and mobile devices, with adaptive controls and a responsive design that adjusts to fit any screen size.<\/p>\n<p>With its no-download requirement, you can play <strong>infinite soccer<\/strong> anywhere, anytime, as long as you have an internet connection.<\/p>\n\n<h2>Strategies and Tips<\/h2>\n<p>Here are some strategies and tips to help you improve your game:<\/p>\n<ul>\n<li>Practice your movement and shooting skills in the early levels to get a feel for the game.<\/li>\n<li>Use the power-ups and bonuses strategically to give you an edge over your opponents.<\/li>\n<li>Pay attention to your opponents' movements and anticipate their next move.<\/li>\n<\/ul>\n\n<h2>Common Mistakes to Avoid<\/h2>\n<table>\n<thead>\n<tr>\n<th>Mode<\/th>\n<th>Difficulty<\/th>\n<th>Recommended Strategy<\/th>\n<th>Common Mistakes<\/th>\n<\/tr>\n<\/thead>\n<tbody>\n<tr>\n<td>Classic<\/td>\n<td>Easy<\/td>\n<td>Focus on scoring goals quickly and efficiently.<\/td>\n<td>Getting too close to the opponent's goal, making it easy to score.<\/td>\n<\/tr>\n<tr>\n<td>Endless<\/td>\n<td>Medium<\/td>\n<td>Conserve energy and use power-ups strategically.<\/td>\n<td>Wasting power-ups on unnecessary shots.<\/td>\n<\/tr>\n<tr>\n<td>Multiplayer<\/td>\n<td>Hard<\/td>\n<td>Pay attention to opponents' movements and block their shots.<\/td>\n<td>Not communicating with teammates in multiplayer mode.<\/td>\n<\/tr>\n<\/tbody>\n<\/table>\n\n<h2>Who is <strong>infinite soccer<\/strong> Best For?<\/h2>\n<p><strong>Infinite soccer unblock game<\/strong> is perfect for anyone looking for a fun and challenging online game to play in their browser. Whether you're a casual gamer or a seasoned athlete, this game offers something for everyone.<\/p>\n<p>The game is also great for players of all ages, as it's easy to learn and can be played in short sessions or for extended periods of time.<\/p>\n<p>So why wait? Head over to the game and start playing <strong>infinite soccer<\/strong> today!<\/p>",
    "description_alt": "<h2><strong>Infinite Soccer Unblock Game: Unlock Endless Fun<\/strong><\/h2>\n<p>The <strong>infinite soccer unblock game<\/strong> is an addictive browser-based experience that lets you play soccer without any time limits. With its simple yet engaging gameplay, it's perfect for short breaks at school or work, or for passing the time on your mobile device. The game's ease of access and lack of downloading requirements make it an ideal choice for those who want to experience the thrill of soccer without any hassle.<\/p>\n<br>\n<h2>Replayability and Difficulty Spikes<\/h2>\n<p>So, what makes the <strong>infinite soccer unblock game<\/strong> so replayable? The secret lies in its ability to adapt to your skill level and provide an increasingly challenging experience. As you progress, the opponents get tougher, and the goals become harder to score. But don't worry, the game doesn't get too frustrating – the difficulty spikes are well-balanced, and you can always come back to it after a break. This ensures that you'll always find a reason to come back and play some more.<\/p>\n<p>One of the key factors that contribute to the game's replayability is its procedurally generated opponents. Each match features a new set of players with unique abilities and playstyles, keeping the experience fresh and exciting. You'll need to adapt your strategy to counter their strengths and weaknesses, which is where the game's depth lies.<\/p>\n<br>\n<h2>Common Player Mistakes and How to Fix Them<\/h2>\n<p>As with any game, there are common mistakes that new players make. One of the most frequent errors is trying to tackle the ball too aggressively, which can result in losing possession. To avoid this, focus on using your opponent's speed and agility against them. Use a combination of quick passes and clever positioning to outmaneuver them and create scoring opportunities.<\/p>\n<p>Another common mistake is neglecting to use your special abilities. In the <strong>infinite soccer unblock game<\/strong>, these abilities can be a game-changer. Make sure to use them wisely to turn the tide of the match in your favor. For example, if you're facing a tough opponent, use your special ability to slow them down and create a gap for a shot on goal.<\/p>\n<br>\n<h2>Strategy Progression: From Beginner to Master<\/h2>\n<p>When you first start playing the <strong>infinite soccer unblock game<\/strong>, it's essential to focus on learning the basics. Spend the first 10 minutes getting familiar with the controls, the ball's movement, and the opponent's AI. As you become more comfortable, you can start to develop your own strategy.<\/p>\n<p>After mastering the basics, you'll enter the mastery phase. This is where you'll refine your skills and develop more complex strategies. You'll need to analyze your opponents' strengths and weaknesses, identify patterns, and adapt your playstyle accordingly. This is the phase where the game truly comes alive, and you'll start to see the results of your hard work.<\/p>\n<br>\n<h2>Mobile Friendliness and Break Suitability<\/h2>\n<p>One of the best things about the <strong>infinite soccer unblock game<\/strong> is its mobile friendliness. The game is designed to be played on any device, including smartphones and tablets. This means you can take the game with you wherever you go and play it during your breaks at school or work.<\/p>\n<p>Speaking of breaks, the game is perfect for short sessions. It's easy to pick up and play, and you can always come back to it later. The game's design ensures that you can play a few matches in a row without getting too frustrated or bored.<\/p>\n<br>\n<h2>Comparison with Similar Browser Games<\/h2>\n<table>\n  <thead>\n    <tr>\n      <th>Game<\/th>\n      <th>Pace<\/th>\n      <th>Skill Ceiling<\/th>\n      <th>Session Length<\/th>\n      <th>Accessibility<\/th>\n    <\/tr>\n  <\/thead>\n  <tbody>\n    <tr>\n      <td><strong>infinite soccer unblock game<\/strong><\/td>\n      <td>Fast-paced<\/td>\n      <td>High<\/td>\n      <td>Short to medium<\/td>\n      <td>Easy<\/td>\n    <\/tr>\n    <tr>\n      <td>Another Browser Soccer Game<\/td>\n      <td>Medium-paced<\/td>\n      <td>Medium<\/td>\n      <td>Medium to long<\/td>\n      <td>Medium<\/td>\n    <\/tr>\n    <tr>\n      <td>Yet Another Browser Game<\/td>\n      <td>Slow-paced<\/td>\n      <td>Low<\/td>\n      <td>Short<\/td>\n      <td>Easy<\/td>\n    <\/tr>\n    <tr>\n      <td>Yet Another Browser Game<\/td>\n      <td>Fast-paced<\/td>\n      <td>High<\/td>\n      <td>Medium<\/td>\n      <td>Medium<\/td>\n    <\/tr>\n  <\/tbody>\n<\/table>\n<br>\n<h2>Pros and Cons of the Game<\/h2>\n<ul>\n  <li>Pros:\n    <ul>\n      <li>Easy to play and pick up<\/li>\n      <li>High replayability due to procedurally generated opponents<\/li>\n      <li>Perfect for short breaks at school or work<\/li>\n    <\/ul>\n  <\/li>\n  <li>Cons:\n    <ul>\n      <li>May get frustrating at times due to difficulty spikes<\/li>\n      <li>Limited depth in terms of gameplay mechanics<\/li>\n    <\/ul>\n  <\/li>\n<\/ul>",
    "questions": [
        {
            "question": "What is infinite soccer and what should new players focus on?",
            "answer": "infinite soccer is a browser sports game where timing and decision-making matter most. Learn the basic mechanics first, then optimize tactics."
        },
        {
            "question": "How can I win more consistently in infinite soccer?",
            "answer": "Focus on fundamentals like positioning, tempo, and clean execution. Consistent simple plays usually beat risky highlight attempts."
        },
        {
            "question": "Why do I make repeated mistakes in infinite soccer?",
            "answer": "Repeated mistakes often come from rushed decisions under pressure. Slow down key moments and play around your strongest patterns."
        },
        {
            "question": "What are the best tips for competitive matches in infinite soccer?",
            "answer": "Adapt your approach based on momentum and opponent behavior. Small tactical adjustments during a match can decide close results."
        },
        {
            "question": "Can I play infinite soccer casually in short sessions?",
            "answer": "Yes, most sports browser games work well in quick sessions. Use short practice rounds to sharpen one skill at a time."
        },
        {
            "question": "Are there similar sports games to infinite soccer?",
            "answer": "Yes, try titles with similar pace and control style. Rotating between comparable games helps improve reaction and tactical reading."
        },
        {
            "question": "Can I play infinite soccer on mobile devices?",
            "answer": "In most cases, infinite soccer runs on modern mobile browsers, but controls can feel different from desktop. Use landscape mode and a stable connection for better responsiveness."
        },
        {
            "question": "Is infinite soccer unblock game free to play?",
            "answer": "Yes, browser games like this are usually free and do not require installation. Open the game page directly and start playing after it finishes loading."
        },
        {
            "question": "What should I do if infinite soccer is laggy or not loading?",
            "answer": "Refresh the page, close unused tabs, and switch to a stable network. If the issue continues, try another browser and disable heavy extensions."
        },
        {
            "question": "Is infinite soccer suitable for short breaks at school or work?",
            "answer": "Yes, most sessions are short and quick to start, so it is suitable for short breaks. Play in smaller sessions and pause between runs to stay consistent."
        }
    ],
    "related_keywords": [
        "infinite soccer online game",
        "infinite soccer unblocked at school",
        "infinite soccer unblocked games 911",
        "play infinite soccer online free",
        "infinite soccer no download",
        "how to play infinite soccer game",
        "infinite soccer controls walkthrough",
        "infinite soccer tips and tricks",
        "infinite soccer mobile game download",
        "infinite soccer browser game online",
        "infinite soccer similar games like",
        "infinite soccer strategy guide",
        "infinite soccer unblocked for kids",
        "infinite soccer online multiplayer game",
        "infinite soccer game online free play",
        "infinite soccer no flash required",
        "infinite soccer online game on browser",
        "infinite soccer mobile game free",
        "infinite soccer game similar to",
        "infinite soccer online game strategy"
    ]
}