{
    "title": "Stickman Bridge Constructor",
    "title_blog": "Stickman Bridge Constructor Unblocked: Tips to Beat the Levels",
    "meta_description": "\"Build and balance your very own stickman bridge in this addictive unblock game, play it now in your browser for free, no downloads needed!\"",
    "meta_description_blog": "\"Master the art of stickman bridge constructor with expert tips and strategies to beat the unblock game on any level.\"",
    "description": "<strong>Get ready to build your way to success with the addictive <strong>Stickman Bridge Constructor unblock game<\/strong>!<\/strong>\nPitting your engineering skills against the laws of physics, Stickman Bridge Constructor is a thrilling online experience that challenges you to construct bridges for stickmen to cross safely. With its intuitive controls and varied levels, it's no wonder this game has become a favorite among browser gamers.\n\n<h2>Core Gameplay and Win Conditions<\/h2>\n<p>In Stickman Bridge Constructor, your goal is to design and build bridges for stickmen to reach the other side of the river. The game takes place on a series of increasingly challenging levels, each with its own unique requirements and obstacles. Your stickmen will be transported across the river by your constructed bridges, and the goal is to keep them safe and sound.<\/p>\n<p>As you progress through the levels, you'll encounter various types of terrain, including water, mud, and obstacles like rocks and traffic. The better you design your bridges, the more stickmen will survive the journey, and the higher your score will be. Sounds simple, but it's not as easy as it sounds – you'll need to balance strength, weight, and structural integrity to succeed.<\/p>\n<p>Winning conditions are straightforward: keep as many stickmen alive as possible, and you'll progress to the next level. Sounds easy, but the game becomes increasingly difficult as you progress, with obstacles and constraints that will test your bridge-building skills to the limit.\n\n<h2>Controls and Gameplay Adaptation<\/h2>\n<p>Stickman Bridge Constructor features intuitive controls that work seamlessly on both desktop and mobile devices. On desktop, you'll use your mouse to click and drag the construction materials to build your bridges. On mobile, touch controls are just as responsive, with swipe gestures allowing you to place and manipulate materials with ease.<\/p>\n<p>One of the standout features of Stickman Bridge Constructor is its adaptability. Whether you're playing on a high-end gaming PC or a budget-friendly smartphone, the game runs smoothly and without a hitch. This is thanks to its browser-based platform, allowing you to play directly in your favorite web browser with no need for downloads or installations.<\/p>\n<p>No matter where you play, the game's controls remain the same, making it easy to pick up and play on the go or in short sessions on your desktop.\n\n<h2>Performance and Browser Compatibility<\/h2>\n<p>Stickman Bridge Constructor is designed to run smoothly in most modern web browsers, including Google Chrome, Mozilla Firefox, and Microsoft Edge. The game's performance is optimized to ensure seamless gameplay, even on lower-end devices.<\/p>\n<p>One of the best things about playing Stickman Bridge Constructor in a browser is the quick-load value – no need to wait for downloads or installations, you can start playing straight away. This also means you can play on any device with a compatible browser, making it a great option for families or friends who want to play together.<\/p>\n<p>For those with older devices or lower-end browsers, the game still runs smoothly, with a smaller file size and optimized code allowing it to run on even the most basic of systems.\n\n<h2>Beginner and Intermediate Tips<\/h2>\n<p>If you're new to Stickman Bridge Constructor, here are some beginner tips to get you started:<\/p>\n<ul>\n<li>Start with simple levels and gradually increase the difficulty as you gain experience.<\/li>\n<li>Focus on building sturdy bridges with a strong foundation and plenty of support.<\/li>\n<li>Experiment with different materials and designs to find what works best for each level.<\/li>\n<\/ul>\n<p>For intermediate players, here are some additional tips to take your gameplay to the next level:<\/p>\n<ul>\n<li>Pay attention to the terrain and obstacles on each level, and adjust your design accordingly.<\/li>\n<li>Use your materials wisely – don't be afraid to experiment with different combinations to achieve the best results.<\/li>\n<li>Keep an eye on your stickmen's progress and adjust your design on the fly to optimize their chances of survival.<\/li>\n<\/ul>\n\n<h2>Who is Stickman Bridge Constructor for?<\/h2>\n<p>Stickman Bridge Constructor is perfect for anyone looking for a fun and challenging engineering-based puzzle game. Whether you're a seasoned gamer or just looking for a new challenge, this game offers something for everyone.<\/p>\n<p>It's great for kids and adults alike, with a simple yet engaging gameplay mechanic that's easy to pick up but difficult to master. The game's addictive nature means you'll find yourself coming back for more, trying to improve your scores and beat your previous high scores.\n\n<h2>Common Mistakes to Avoid<\/h2>\n<table>\n<thead>\n<tr><th>Mode<\/th><th>Difficulty<\/th><th>Recommended Strategy<\/th><th>Common Mistakes<\/th><\/tr>\n<\/thead>\n<tbody>\n<tr><td>Timed Mode<\/td><td>Expert<\/td><td>Focus on building strong, high bridges that can withstand the pressure.<\/td><td>Building too many weak bridges in a row, leading to a high failure rate.<\/tr>\n<tr><td>Free Play<\/td><td>Easy<\/td><td>Experiment with different materials and designs to find what works best for each level.<\/td><td>Getting too attached to a particular design and not adapting to changing circumstances.<\/tr>\n<tr><td>Challenge Mode<\/td><td>Hard<\/td><td>Pay attention to the terrain and obstacles on each level, and adjust your design accordingly.<\/td><td>Not testing different materials and designs before committing to a build.<\/tr>\n<\/tbody>\n<\/table>\n\n<h2>Unblocked Access and Playing Online<\/h2>\n<p>One of the best things about Stickman Bridge Constructor is its unblocked access – you can play directly in your favorite web browser, no need for downloads or installations. This means you can play on any device with a compatible browser, making it a great option for families or friends who want to play together.<\/p>\n<p>With no need to download the game, you can start playing immediately, and with its optimized code and smaller file size, it runs smoothly on even the most basic of systems. This is perfect for those with older devices or lower-end browsers, who can still enjoy the full Stickman Bridge Constructor experience.",
    "description_alt": "<h2>Unleash Your Engineering Skills with <strong>Stickman Bridge Constructor Unblock Game<\/strong><\/h2>\n<p>Get ready to test your engineering prowess and creativity in this addictive and challenging online game, Stickman Bridge Constructor Unblock. With its unique blend of physics-based puzzle-solving and stickman-themed visuals, this game is sure to captivate players of all ages and skill levels. By mastering the art of bridge construction, you'll unlock new levels, overcome obstacles, and experience the thrill of victory in this exciting browser game.<\/p>\n<p>One of the key factors that sets Stickman Bridge Constructor Unblock apart from other online games is its high replay value. With an almost endless supply of levels and challenges, you'll never run out of new puzzles to solve and new skills to master. Whether you're a casual player or a seasoned gamer, this game is designed to keep you engaged and entertained for hours on end.<\/p>\n\n<h2>Where Difficulty Spikes Happen and How to Overcome Them<\/h2>\n<p>As you progress through the game, you'll encounter increasingly challenging levels that will put your engineering skills to the test. But don't worry – with practice and patience, you'll develop the expertise needed to overcome even the toughest obstacles. To help you get started, here are a few tips to keep in mind:<\/p>\n<p>• Start with simple levels and gradually work your way up to more complex challenges. This will help you build a strong foundation and develop a deeper understanding of the game's mechanics.<\/p>\n<p>• Pay attention to the game's physics engine and learn how to use it to your advantage. By understanding how the game's physics work, you'll be able to create more efficient and effective bridge designs.<\/p>\n\n<h2>Common Player Mistakes and How to Fix Them<\/h2>\n<p>Despite its simplicity, Stickman Bridge Constructor Unblock can be a challenging game, especially for new players. Here are a few common mistakes to watch out for and how to fix them:<\/p>\n<p>• <strong>Mistake 1:<\/strong> Insufficient bridge support – Make sure to provide adequate support for your bridges to prevent them from collapsing.<\/p>\n<p>• <strong>Mistake 2:<\/strong> Inadequate material usage – Use materials efficiently to minimize waste and maximize bridge strength.<\/p>\n\n<h2>Strategy Progression: From Beginner to Mastery<\/h2>\n<p>As you progress through the game, you'll need to adapt your strategy to overcome increasingly challenging levels. Here's a rough outline of what you can expect:<\/p>\n<p>• <strong>First 10 minutes:<\/strong> Focus on getting familiar with the game's mechanics and building simple bridges.<\/p>\n<p>• <strong>After basics:<\/strong> Experiment with different materials and designs to find the most efficient solutions.<\/p>\n<p>• <strong>Mastery phase:<\/strong> Develop a deep understanding of the game's physics engine and use it to create complex and innovative bridge designs.<\/p>\n\n<h2>Mobile Friendliness and School\/Work Break Suitability<\/h2>\n<p>One of the best things about Stickman Bridge Constructor Unblock is its mobile friendliness. Whether you're playing on a tablet or smartphone, the game is designed to be easy to use and navigate, making it perfect for playing during school or work breaks. Plus, with no installation required, you can start playing right away – no downloads or installations needed!<\/p>\n\n<h2>Stickman Bridge Constructor Unblock Game: A Comparison with Similar Browser Games<\/h2>\n<table>\n<thead>\n<tr>\n<th>Game<\/th>\n<th>Pace<\/th>\n<th>Skill Ceiling<\/th>\n<th>Session Length<\/th>\n<th>Accessibility<\/th>\n<\/tr>\n<\/thead>\n<tbody>\n<tr>\n<td>Stickman Bridge Constructor Unblock<\/td>\n<td>Medium<\/td>\n<td>High<\/td>\n<td>Variable<\/td>\n<td>Easy<\/td>\n<\/tr>\n<tr>\n<td>Bridge Builder<\/td>\n<td>Fast<\/td>\n<td>Medium<\/td>\n<td>Short<\/td>\n<td>Medium<\/td>\n<\/tr>\n<tr>\n<td>Bridge Constructor<\/td>\n<td>Slow<\/td>\n<td>High<\/td>\n<td>Long<\/td>\n<td>Hard<\/td>\n<\/tr>\n<tr>\n<td>Stickman Bridge<\/td>\n<td>Medium<\/td>\n<td>Medium<\/td>\n<td>Variable<\/td>\n<td>Easy<\/td>\n<\/tr>\n<\/tbody>\n<\/table>\n\n<h2>Pros and Cons of Stickman Bridge Constructor Unblock Game<\/h2>\n<ul>\n<li><strong>Pros:<\/strong> High replay value, easy to learn, challenging to master, mobile friendly, no installation required.<\/li>\n<li><strong>Cons:<\/strong> Some levels can be frustratingly difficult, may require patience and practice to overcome.<\/li>\n<\/ul>",
    "questions": [
        {
            "question": "What is stickman bridge constructor and what is the goal?",
            "answer": "stickman bridge constructor is a browser platform game that tests movement precision and timing. The main goal is to clear stages by mastering jumps and routes."
        },
        {
            "question": "How can beginners survive longer in stickman bridge constructor?",
            "answer": "Start slower and memorize obstacle patterns before pushing speed. Consistent route execution is more valuable than risky shortcuts."
        },
        {
            "question": "Why do I fail the same section in stickman bridge constructor?",
            "answer": "Most repeated failures come from mistimed jumps or poor rhythm. Practice the section in short focused attempts until the timing becomes automatic."
        },
        {
            "question": "What are advanced tips for stickman bridge constructor?",
            "answer": "Chain movement cleanly and reduce unnecessary corrections. Efficient pathing and rhythm control usually create the biggest improvements."
        },
        {
            "question": "Can stickman bridge constructor be played well on mobile?",
            "answer": "Yes, but touch controls may require adaptation time. Use stable thumb placement and avoid overcrowded screen gestures for better control."
        },
        {
            "question": "Are there games like stickman bridge constructor for practice?",
            "answer": "Yes, similar platform and runner games can sharpen your timing and pattern reading. Cross-training improves consistency across difficult stages."
        },
        {
            "question": "Can I play stickman bridge constructor on mobile devices?",
            "answer": "In most cases, stickman bridge constructor runs on modern mobile browsers, but controls can feel different from desktop. Use landscape mode and a stable connection for better responsiveness."
        },
        {
            "question": "Is stickman bridge constructor unblock game free to play?",
            "answer": "Yes, browser games like this are usually free and do not require installation. Open the game page directly and start playing after it finishes loading."
        },
        {
            "question": "What should I do if stickman bridge constructor is laggy or not loading?",
            "answer": "Refresh the page, close unused tabs, and switch to a stable network. If the issue continues, try another browser and disable heavy extensions."
        },
        {
            "question": "Is stickman bridge constructor suitable for short breaks at school or work?",
            "answer": "Yes, most sessions are short and quick to start, so it is suitable for short breaks. Play in smaller sessions and pause between runs to stay consistent."
        }
    ],
    "related_keywords": [
        "stickman bridge constructor unblocked",
        "stickman bridge constructor online game",
        "stickman bridge constructor browser game",
        "stickman bridge constructor no download",
        "stickman bridge constructor tips",
        "stickman bridge constructor controls",
        "stickman bridge constructor mobile game",
        "stickman bridge constructor strategy guide",
        "stickman bridge constructor similar games",
        "free stickman bridge constructor game",
        "online stickman bridge constructor game",
        "stickman bridge constructor walkthrough",
        "stickman bridge constructor cheats",
        "stickman bridge constructor level 1",
        "stickman bridge constructor level 1-10",
        "stickman bridge constructor easy levels",
        "stickman bridge constructor hard levels",
        "stickman bridge constructor bridge builder game",
        "stickman bridge constructor puzzle game",
        "no-download stickman bridge constructor"
    ]
}